haystack_integrations/components/embedders/voyage_embedders/__init__.py
haystack_integrations/components/embedders/voyage_embedders/voyage_contextualized_document_embedder.py
haystack_integrations/components/embedders/voyage_embedders/voyage_document_embedder.py
haystack_integrations/components/embedders/voyage_embedders/voyage_multimodal_embedder.py
haystack_integrations/components/embedders/voyage_embedders/voyage_text_embedder.py
haystack_integrations/components/rankers/voyage/__init__.py
haystack_integrations/components/rankers/voyage/ranker.py
voyage_embedders_haystack-1.9.0.dist-info/WHEEL
voyage_embedders_haystack-1.9.0.dist-info/METADATA
voyage_embedders_haystack-1.9.0.dist-info/RECORD
