Metadata-Version: 2.4
Name: voyage-embedders-haystack
Version: 1.9.0
Summary: Haystack component to embed strings and Documents using VoyageAI Embedding models.
Keywords: Haystack,VoyageAI,Embedding,Rankers,Semantic Search
Author: Ashwin Mathur
License-Expression: Apache-2.0
Classifier: Development Status :: 5 - Production/Stable
Classifier: Intended Audience :: Science/Research
Classifier: Operating System :: OS Independent
Classifier: Programming Language :: Python
Classifier: Programming Language :: Python :: 3
Classifier: Topic :: Scientific/Engineering :: Artificial Intelligence
Requires-Dist: haystack-ai
Requires-Dist: typing-extensions
Requires-Dist: numpy
Requires-Dist: voyageai>=0.3.7
Maintainer: Ashwin Mathur
Requires-Python: >=3.10
Project-URL: Documentation, https://github.com/awinml/voyage-embedders-haystack#readme
Project-URL: Issues, https://github.com/awinml/voyage-embedders-haystack/issues
Project-URL: Source, https://github.com/awinml/voyage-embedders-haystack
